funcs/__init__.py
funcs/application.py
funcs/callers.py
funcs/composition.py
funcs/debugging.py
funcs/decorators.py
funcs/flows.py
funcs/functions.py
funcs/getters.py
funcs/primitives.py
funcs/py.typed
funcs/reduction.py
funcs/types.py
funcs/unpacking.py
funcs-0.10.0.dist-info/LICENSE
funcs-0.10.0.dist-info/METADATA
funcs-0.10.0.dist-info/WHEEL
funcs-0.10.0.dist-info/RECORD
