Metadata-Version: 2.1
Name: funcs
Version: 0.10.0
Summary: Functional programming in Python.
Home-page: https://github.com/nekitdev/funcs
License: MIT
Keywords: python,function,functional,paradigm
Author: nekitdev
Requires-Python: >=3.8
Classifier: Development Status :: 5 - Production/Stable
Classifier: Intended Audience :: Developers
Classifier: License :: OSI Approved :: MIT License
Classifier: Operating System :: OS Independent
Classifier: Programming Language :: Python :: 3
Classifier: Programming Language :: Python :: 3.8
Classifier: Programming Language :: Python :: 3.9
Classifier: Programming Language :: Python :: 3.10
Classifier: Programming Language :: Python :: 3.11
Classifier: Programming Language :: Python :: 3.12
Classifier: Topic :: Utilities
Classifier: Typing :: Typed
Requires-Dist: solus (>=1.2.2)
Requires-Dist: typing-aliases (>=1.10.0)
Requires-Dist: typing-extensions (>=4.10.0)
Project-URL: Chat, https://nekit.dev/chat
Project-URL: Documentation, https://nekitdev.github.io/funcs
Project-URL: Funding, https://nekit.dev/funding
Project-URL: Issues, https://github.com/nekitdev/funcs/issues
Project-URL: Repository, https://github.com/nekitdev/funcs
